experimentflow/__init__.py
experimentflow/factor.py
experimentflow-0.1.0a2.dist-info/METADATA
experimentflow-0.1.0a2.dist-info/WHEEL
experimentflow-0.1.0a2.dist-info/RECORD
