Metadata-Version: 2.1
Name: experimentflow
Version: 0.1.0a2
Summary: ExperimentFlow is a library to help you manage your experiments in a more organized way.
Home-page: https://github.com/domingoslatorre/experimentflow
Author: Domingos Latorre
Author-email: domingos.latorre@gmail.com
Requires-Python: >=3.10,<4.0
Classifier: Programming Language :: Python :: 3
Classifier: Programming Language :: Python :: 3.10
Classifier: Programming Language :: Python :: 3.11
Classifier: Programming Language :: Python :: 3.12
Project-URL: Repository, https://github.com/domingoslatorre/experimentflow
